{"box_data": [{"position": {"minX": 236.375, "minY": 280.75, "maxX": 278.5, "maxY": 314.25}, "class_id": 0, "box_caption": "ball 0.848", "scores": {"class_score": 0.84765625}, "domain": "pixel"}, {"position": {"minX": 639.5, "minY": 240.75, "maxX": 653.5, "maxY": 277.75}, "class_id": 0, "box_caption": "ball 0.064", "scores": {"class_score": 0.06396484375}, "domain": "pixel"}, {"position": {"minX": 641.0, "minY": 236.625, "maxX": 658.0, "maxY": 280.0}, "class_id": 0, "box_caption": "ball 0.060", "scores": {"class_score": 0.059722900390625}, "domain": "pixel"}, {"position": {"minX": 242.0, "minY": 15.5859375, "maxX": 264.5, "maxY": 35.75}, "class_id": 0, "box_caption": "ball 0.049", "scores": {"class_score": 0.049224853515625}, "domain": "pixel"}, {"position": {"minX": 432.25, "minY": 123.0625, "maxX": 491.25, "maxY": 167.0}, "class_id": 0, "box_caption": "ball 0.025", "scores": {"class_score": 0.025299072265625}, "domain": "pixel"}, {"position": {"minX": 229.125, "minY": 11.6484375, "maxX": 268.25, "maxY": 38.40625}, "class_id": 0, "box_caption": "ball 0.013", "scores": {"class_score": 0.01306915283203125}, "domain": "pixel"}, {"position": {"minX": 238.75, "minY": 15.6484375, "maxX": 278.75, "maxY": 40.53125}, "class_id": 0, "box_caption": "ball 0.011", "scores": {"class_score": 0.01116180419921875}, "domain": "pixel"}, {"position": {"minX": 233.25, "minY": 276.0, "maxX": 269.0, "maxY": 318.5}, "class_id": 0, "box_caption": "ball 0.011", "scores": {"class_score": 0.0110015869140625}, "domain": "pixel"}, {"position": {"minX": 440.75, "minY": 159.5, "maxX": 479.25, "maxY": 194.5}, "class_id": 0, "box_caption": "ball 0.010", "scores": {"class_score": 0.0101470947265625}, "domain": "pixel"}, {"position": {"minX": 236.25, "minY": 273.75, "maxX": 286.75, "maxY": 321.75}, "class_id": 0, "box_caption": "ball 0.010", "scores": {"class_score": 0.0098419189453125}, "domain": "pixel"}, {"position": {"minX": 622.5, "minY": 100.4375, "maxX": 656.5, "maxY": 134.25}, "class_id": 0, "box_caption": "ball 0.008", "scores": {"class_score": 0.00823211669921875}, "domain": "pixel"}, {"position": {"minX": 631.5, "minY": 238.25, "maxX": 662.5, "maxY": 272.75}, "class_id": 0, "box_caption": "ball 0.007", "scores": {"class_score": 0.00673675537109375}, "domain": "pixel"}, {"position": {"minX": 623.0, "minY": 258.25, "maxX": 656.0, "maxY": 291.75}, "class_id": 0, "box_caption": "ball 0.006", "scores": {"class_score": 0.006053924560546875}, "domain": "pixel"}, {"position": {"minX": 258.25, "minY": 286.5, "maxX": 305.75, "maxY": 316.5}, "class_id": 0, "box_caption": "ball 0.006", "scores": {"class_score": 0.005725860595703125}, "domain": "pixel"}, {"position": {"minX": 241.5, "minY": 276.0, "maxX": 273.0, "maxY": 305.5}, "class_id": 0, "box_caption": "ball 0.006", "scores": {"class_score": 0.005718231201171875}, "domain": "pixel"}, {"position": {"minX": 109.6875, "minY": 33.03125, "maxX": 118.1875, "maxY": 43.40625}, "class_id": 0, "box_caption": "ball 0.006", "scores": {"class_score": 0.005512237548828125}, "domain": "pixel"}, {"position": {"minX": 634.0, "minY": 240.5, "maxX": 655.0, "maxY": 283.0}, "class_id": 0, "box_caption": "ball 0.005", "scores": {"class_score": 0.005100250244140625}, "domain": "pixel"}, {"position": {"minX": 167.25, "minY": 200.375, "maxX": 377.25, "maxY": 410.0}, "class_id": 0, "box_caption": "ball 0.005", "scores": {"class_score": 0.0049896240234375}, "domain": "pixel"}, {"position": {"minX": 433.0, "minY": 166.25, "maxX": 485.0, "maxY": 197.25}, "class_id": 0, "box_caption": "ball 0.003", "scores": {"class_score": 0.0034961700439453125}, "domain": "pixel"}, {"position": {"minX": 234.125, "minY": 290.75, "maxX": 273.0, "maxY": 323.25}, "class_id": 0, "box_caption": "ball 0.003", "scores": {"class_score": 0.0033817291259765625}, "domain": "pixel"}, {"position": {"minX": 439.75, "minY": 152.75, "maxX": 482.25, "maxY": 207.25}, "class_id": 0, "box_caption": "ball 0.003", "scores": {"class_score": 0.0033054351806640625}, "domain": "pixel"}, {"position": {"minX": 623.0, "minY": 235.75, "maxX": 655.0, "maxY": 272.25}, "class_id": 0, "box_caption": "ball 0.003", "scores": {"class_score": 0.0032138824462890625}, "domain": "pixel"}, {"position": {"minX": 243.25, "minY": 288.0, "maxX": 285.25, "maxY": 324.0}, "class_id": 0, "box_caption": "ball 0.003", "scores": {"class_score": 0.0032062530517578125}, "domain": "pixel"}, {"position": {"minX": 134.0, "minY": 172.5, "maxX": 351.5, "maxY": 377.0}, "class_id": 0, "box_caption": "ball 0.003", "scores": {"class_score": 0.0030059814453125}, "domain": "pixel"}, {"position": {"minX": 618.0, "minY": 285.75, "maxX": 651.0, "maxY": 318.25}, "class_id": 0, "box_caption": "ball 0.003", "scores": {"class_score": 0.00276947021484375}, "domain": "pixel"}, {"position": {"minX": 517.0, "minY": 178.5, "maxX": 553.0, "maxY": 213.5}, "class_id": 0, "box_caption": "ball 0.003", "scores": {"class_score": 0.0027370452880859375}, "domain": "pixel"}, {"position": {"minX": 382.5, "minY": 57.25, "maxX": 547.0, "maxY": 230.0}, "class_id": 0, "box_caption": "ball 0.003", "scores": {"class_score": 0.0026416778564453125}, "domain": "pixel"}, {"position": {"minX": 216.25, "minY": -4.203125, "maxX": 274.5, "maxY": 51.5625}, "class_id": 0, "box_caption": "ball 0.003", "scores": {"class_score": 0.0025119781494140625}, "domain": "pixel"}, {"position": {"minX": 427.25, "minY": 143.625, "maxX": 495.75, "maxY": 200.125}, "class_id": 0, "box_caption": "ball 0.002", "scores": {"class_score": 0.0024700164794921875}, "domain": "pixel"}, {"position": {"minX": 198.625, "minY": 285.75, "maxX": 244.625, "maxY": 315.25}, "class_id": 0, "box_caption": "ball 0.002", "scores": {"class_score": 0.0024242401123046875}, "domain": "pixel"}, {"position": {"minX": 108.375, "minY": 35.0, "maxX": 117.375, "maxY": 42.25}, "class_id": 0, "box_caption": "ball 0.002", "scores": {"class_score": 0.00238800048828125}, "domain": "pixel"}, {"position": {"minX": 620.0, "minY": 121.625, "maxX": 654.0, "maxY": 154.625}, "class_id": 0, "box_caption": "ball 0.002", "scores": {"class_score": 0.0023822784423828125}, "domain": "pixel"}, {"position": {"minX": 252.0, "minY": 284.25, "maxX": 280.5, "maxY": 314.75}, "class_id": 0, "box_caption": "ball 0.002", "scores": {"class_score": 0.0023136138916015625}, "domain": "pixel"}, {"position": {"minX": 425.0, "minY": 107.8125, "maxX": 491.5, "maxY": 178.5}, "class_id": 0, "box_caption": "ball 0.002", "scores": {"class_score": 0.002307891845703125}, "domain": "pixel"}, {"position": {"minX": 606.5, "minY": 81.375, "maxX": 661.5, "maxY": 147.875}, "class_id": 0, "box_caption": "ball 0.002", "scores": {"class_score": 0.0022373199462890625}, "domain": "pixel"}, {"position": {"minX": 363.0, "minY": 164.875, "maxX": 404.0, "maxY": 195.625}, "class_id": 0, "box_caption": "ball 0.002", "scores": {"class_score": 0.0021820068359375}, "domain": "pixel"}, {"position": {"minX": 441.0, "minY": 107.1875, "maxX": 488.5, "maxY": 156.875}, "class_id": 0, "box_caption": "ball 0.002", "scores": {"class_score": 0.0021514892578125}, "domain": "pixel"}, {"position": {"minX": 228.125, "minY": -3.28125, "maxX": 299.5, "maxY": 57.96875}, "class_id": 0, "box_caption": "ball 0.002", "scores": {"class_score": 0.00202178955078125}, "domain": "pixel"}, {"position": {"minX": 445.25, "minY": 164.625, "maxX": 473.25, "maxY": 199.125}, "class_id": 0, "box_caption": "ball 0.002", "scores": {"class_score": 0.0019407272338867188}, "domain": "pixel"}, {"position": {"minX": 515.0, "minY": 10.96875, "maxX": 552.0, "maxY": 45.78125}, "class_id": 0, "box_caption": "ball 0.002", "scores": {"class_score": 0.0018072128295898438}, "domain": "pixel"}, {"position": {"minX": 439.0, "minY": 169.125, "maxX": 479.0, "maxY": 204.875}, "class_id": 0, "box_caption": "ball 0.002", "scores": {"class_score": 0.0017499923706054688}, "domain": "pixel"}, {"position": {"minX": 187.75, "minY": 258.0, "maxX": 236.25, "maxY": 291.5}, "class_id": 0, "box_caption": "ball 0.002", "scores": {"class_score": 0.0017347335815429688}, "domain": "pixel"}, {"position": {"minX": 607.0, "minY": 239.125, "maxX": 663.0, "maxY": 307.0}, "class_id": 0, "box_caption": "ball 0.002", "scores": {"class_score": 0.0016717910766601562}, "domain": "pixel"}, {"position": {"minX": 85.5625, "minY": 155.875, "maxX": 129.25, "maxY": 200.625}, "class_id": 0, "box_caption": "ball 0.002", "scores": {"class_score": 0.0016422271728515625}, "domain": "pixel"}, {"position": {"minX": 109.875, "minY": -97.1875, "maxX": 370.0, "maxY": 131.0}, "class_id": 0, "box_caption": "ball 0.002", "scores": {"class_score": 0.0015459060668945312}, "domain": "pixel"}, {"position": {"minX": 507.0, "minY": 4.078125, "maxX": 559.0, "maxY": 56.1875}, "class_id": 0, "box_caption": "ball 0.002", "scores": {"class_score": 0.0015363693237304688}, "domain": "pixel"}, {"position": {"minX": 622.5, "minY": 216.375, "maxX": 680.5, "maxY": 290.0}, "class_id": 0, "box_caption": "ball 0.002", "scores": {"class_score": 0.0015316009521484375}, "domain": "pixel"}, {"position": {"minX": 244.625, "minY": 226.25, "maxX": 287.5, "maxY": 259.75}, "class_id": 0, "box_caption": "ball 0.001", "scores": {"class_score": 0.0014934539794921875}, "domain": "pixel"}, {"position": {"minX": 359.5, "minY": 72.0625, "maxX": 567.5, "maxY": 281.0}, "class_id": 0, "box_caption": "ball 0.001", "scores": {"class_score": 0.0014581680297851562}, "domain": "pixel"}, {"position": {"minX": 305.5, "minY": 34.9375, "maxX": 580.0, "maxY": 258.25}, "class_id": 0, "box_caption": "ball 0.001", "scores": {"class_score": 0.0014581680297851562}, "domain": "pixel"}, {"position": {"minX": 437.5, "minY": 164.75, "maxX": 486.5, "maxY": 187.75}, "class_id": 0, "box_caption": "ball 0.001", "scores": {"class_score": 0.0014219284057617188}, "domain": "pixel"}, {"position": {"minX": 486.75, "minY": -0.3125, "maxX": 767.0, "maxY": 228.0}, "class_id": 0, "box_caption": "ball 0.001", "scores": {"class_score": 0.0013971328735351562}, "domain": "pixel"}, {"position": {"minX": 382.0, "minY": 168.125, "maxX": 421.0, "maxY": 198.875}, "class_id": 0, "box_caption": "ball 0.001", "scores": {"class_score": 0.0013790130615234375}, "domain": "pixel"}, {"position": {"minX": 453.5, "minY": 160.5, "maxX": 494.0, "maxY": 200.0}, "class_id": 0, "box_caption": "ball 0.001", "scores": {"class_score": 0.0013713836669921875}, "domain": "pixel"}, {"position": {"minX": 217.875, "minY": 277.75, "maxX": 284.5, "maxY": 344.25}, "class_id": 0, "box_caption": "ball 0.001", "scores": {"class_score": 0.0013685226440429688}, "domain": "pixel"}, {"position": {"minX": 507.75, "minY": 18.6875, "maxX": 556.0, "maxY": 37.1875}, "class_id": 0, "box_caption": "ball 0.001", "scores": {"class_score": 0.0012989044189453125}, "domain": "pixel"}, {"position": {"minX": 78.25, "minY": 163.75, "maxX": 116.0, "maxY": 199.25}, "class_id": 0, "box_caption": "ball 0.001", "scores": {"class_score": 0.001277923583984375}, "domain": "pixel"}, {"position": {"minX": 431.25, "minY": 118.625, "maxX": 486.75, "maxY": 153.625}, "class_id": 0, "box_caption": "ball 0.001", "scores": {"class_score": 0.0012454986572265625}, "domain": "pixel"}, {"position": {"minX": 247.5, "minY": 273.0, "maxX": 325.0, "maxY": 333.0}, "class_id": 0, "box_caption": "ball 0.001", "scores": {"class_score": 0.0012235641479492188}, "domain": "pixel"}, {"position": {"minX": 183.75, "minY": 69.4375, "maxX": 194.25, "maxY": 79.4375}, "class_id": 0, "box_caption": "ball 0.001", "scores": {"class_score": 0.0012159347534179688}, "domain": "pixel"}, {"position": {"minX": 542.0, "minY": 110.125, "maxX": 769.0, "maxY": 374.0}, "class_id": 0, "box_caption": "ball 0.001", "scores": {"class_score": 0.0011768341064453125}, "domain": "pixel"}, {"position": {"minX": 424.75, "minY": 86.125, "maxX": 498.75, "maxY": 161.375}, "class_id": 0, "box_caption": "ball 0.001", "scores": {"class_score": 0.001171112060546875}, "domain": "pixel"}, {"position": {"minX": 244.375, "minY": 22.609375, "maxX": 260.25, "maxY": 36.34375}, "class_id": 0, "box_caption": "ball 0.001", "scores": {"class_score": 0.0011339187622070312}, "domain": "pixel"}, {"position": {"minX": 232.875, "minY": 271.0, "maxX": 302.5, "maxY": 346.5}, "class_id": 0, "box_caption": "ball 0.001", "scores": {"class_score": 0.0010862350463867188}, "domain": "pixel"}, {"position": {"minX": 360.5, "minY": 188.75, "maxX": 402.5, "maxY": 218.75}, "class_id": 0, "box_caption": "ball 0.001", "scores": {"class_score": 0.00106048583984375}, "domain": "pixel"}, {"position": {"minX": 596.5, "minY": 265.5, "maxX": 666.5, "maxY": 338.5}, "class_id": 0, "box_caption": "ball 0.001", "scores": {"class_score": 0.0010509490966796875}, "domain": "pixel"}, {"position": {"minX": 604.0, "minY": 211.5, "maxX": 665.0, "maxY": 289.0}, "class_id": 0, "box_caption": "ball 0.001", "scores": {"class_score": 0.0010471343994140625}, "domain": "pixel"}, {"position": {"minX": 602.0, "minY": 101.5625, "maxX": 664.0, "maxY": 172.0}, "class_id": 0, "box_caption": "ball 0.001", "scores": {"class_score": 0.00104522705078125}, "domain": "pixel"}, {"position": {"minX": 501.75, "minY": 159.75, "maxX": 567.5, "maxY": 228.0}, "class_id": 0, "box_caption": "ball 0.001", "scores": {"class_score": 0.0010213851928710938}, "domain": "pixel"}], "class_labels": {"0": "ball"}}